orbipyd/__init__.py
orbipyd/correction.py
orbipyd/detect_event.py
orbipyd/events.py
orbipyd/integrator.py
orbipyd/model.py
orbipyd/orbi_data.csv
orbipyd/project_test_1.py
orbipyd/station_keeping.py
orbipyd/test.py
orbipyd1/__init__.py
orbipyd1/correction.py
orbipyd1/detect_event.py
orbipyd1/events.py
orbipyd1/integrator.py
orbipyd1/model.py
orbipyd1/orbi_data.csv
orbipyd1/project_test_1.py
orbipyd1/station_keeping.py
orbipyd-4.dist-info/LICENSE
orbipyd-4.dist-info/METADATA
orbipyd-4.dist-info/WHEEL
orbipyd-4.dist-info/top_level.txt
orbipyd-4.dist-info/RECORD
